{
  "name": "braden",
  "website": "https://theworld.exposed",
  "date": "2026-05-04T12:00:00-07:00",
  "words": [
    {"text": "beautiful", "x": 123, "y": 83, "rotation": -0.8},
    {"text": "dying", "x": 568, "y": 348, "rotation": 1.6},
    {"text": "up", "x": 108, "y": 840, "rotation": -0.3},
    {"text": "honeydew", "x": 344, "y": 502, "rotation": 1.5},
    {"text": "bark", "x": 1045, "y": 186, "rotation": -2.4},
    {"text": "vine", "x": 1044, "y": 847, "rotation": -0.8},
    {"text": "no", "x": 10, "y": 204, "rotation": -0.9},
    {"text": "embrace", "x": 959, "y": 737, "rotation": 2.5},
    {"text": "watch", "x": 1059, "y": 76, "rotation": 1.1},
    {"text": "soak", "x": 1056, "y": 138, "rotation": -0.1},
    {"text": "inside", "x": 82, "y": 787, "rotation": 2.5},
    {"text": "but", "x": 492, "y": 439, "rotation": -0.3},
    {"text": "storm", "x": 1039, "y": 750, "rotation": 1.4},
    {"text": "on", "x": 979, "y": 852, "rotation": -0.3},
    {"text": "drift", "x": 998, "y": 28, "rotation": -0.1},
    {"text": "as", "x": 548, "y": 541, "rotation": 2.9},
    {"text": "might", "x": 643, "y": 495, "rotation": -0.4},
    {"text": "barely", "x": 416, "y": 523, "rotation": 1.8},
    {"text": "moth", "x": 210, "y": 158, "rotation": 1.9},
    {"text": "an", "x": 1080, "y": 28, "rotation": 0.4},
    {"text": "twin", "x": 982, "y": 118, "rotation": 2.5},
    {"text": "shimmering", "x": 454, "y": 555, "rotation": 0.3},
    {"text": "clumsily", "x": 1003, "y": 793, "rotation": -1.7},
    {"text": "still", "x": 127, "y": 39, "rotation": 0},
    {"text": "dry", "x": 908, "y": 22, "rotation": -1.6},
    {"text": "first", "x": 309, "y": 477, "rotation": -3},
    {"text": "poison", "x": 64, "y": 219, "rotation": 2.1},
    {"text": "their", "x": 47, "y": 43, "rotation": -2.9},
    {"text": "cruelly", "x": 401, "y": 341, "rotation": -1.8},
    {"text": "stream", "x": 26, "y": 846, "rotation": -1.7},
    {"text": "touch", "x": 55, "y": 85, "rotation": -3},
    {"text": "roam", "x": 24, "y": 771, "rotation": 1.1},
    {"text": "woods", "x": 979, "y": 73, "rotation": 0.5},
    {"text": "noiselessly", "x": 44, "y": 133, "rotation": 2.4},
    {"text": "seawater", "x": 575, "y": 521, "rotation": 1.8}
  ]
}
